setup.py
campaign_metrics_julie_data/Emailcampaign.py
campaign_metrics_julie_data/Generalcampaign.py
campaign_metrics_julie_data/Websitecampaign.py
campaign_metrics_julie_data/__init__.py
campaign_metrics_julie_data/test.py
campaign_metrics_julie_data.egg-info/PKG-INFO
campaign_metrics_julie_data.egg-info/SOURCES.txt
campaign_metrics_julie_data.egg-info/dependency_links.txt
campaign_metrics_julie_data.egg-info/not-zip-safe
campaign_metrics_julie_data.egg-info/top_level.txt