Metadata-Version: 1.0
Name: campaign-metrics-julie-data
Version: 0.1
Summary: Measures of campaigns per email and on site
Home-page: UNKNOWN
Author: Julie Trinco
Author-email: julie_trinco@hotmail.com
License: UNKNOWN
Platform: UNKNOWN
